commitlens.py
commitlens-0.1.0.dist-info/LICENSE
commitlens-0.1.0.dist-info/METADATA
commitlens-0.1.0.dist-info/WHEEL
commitlens-0.1.0.dist-info/entry_points.txt
commitlens-0.1.0.dist-info/top_level.txt
commitlens-0.1.0.dist-info/RECORD
