Metadata-Version: 2.2
Name: commitlens
Version: 0.1.0
Summary: Git Change Visualization Tool with AI-powered summaries
Home-page: https://github.com/alessandrodorazio/commitlens
Author: Alessandro D'Orazio
Author-email: me@alessandrodorazio.it
Classifier: Programming Language :: Python :: 3
Classifier: License :: OSI Approved :: MIT License
Classifier: Operating System :: OS Independent
Requires-Python: >=3.6
License-File: LICENSE
Requires-Dist: openai>=1.0.0
Requires-Dist: tiktoken>=0.5.0
Requires-Dist: rich>=13.0.0
Dynamic: author
Dynamic: author-email
Dynamic: classifier
Dynamic: description
Dynamic: description-content-type
Dynamic: home-page
Dynamic: requires-dist
Dynamic: requires-python
Dynamic: summary
